anypay/__init__.py
anypay/api.py
anypay/exceptions.py
anypay/models/__init__.py
anypay/models/bill.py
anypay/models/payment.py
anypay/models/payout.py
anypay/models/rates.py
anypay-1.1.4.dist-info/LICENSE
anypay-1.1.4.dist-info/METADATA
anypay-1.1.4.dist-info/WHEEL
anypay-1.1.4.dist-info/top_level.txt
anypay-1.1.4.dist-info/RECORD
