Metadata-Version: 2.1
Name: anypay
Version: 1.1.4
Summary: Asynchronous AnyPay API wrapper
Home-page: https://github.com/nikitalm8/anypay
Author: Nikita Minaev
Author-email: <nikita@minaev.su>
Project-URL: Homepage, https://github.com/nikitalm8/anypay
Project-URL: Bug Tracker, https://github.com/nikitalm8/anypay/issues
Project-URL: API Docs, https://anypay.io/doc/api
Keywords: python,anypay,payments,anypay-api,async,asyncio
Classifier: Development Status :: 4 - Beta
Classifier: Intended Audience :: Developers
Classifier: Programming Language :: Python :: 3
Classifier: Operating System :: Unix
Classifier: Operating System :: MacOS :: MacOS X
Classifier: Operating System :: Microsoft :: Windows
License-File: LICENSE
Requires-Dist: httpx
Requires-Dist: pydantic
